tsdisagg/__init__.py
tsdisagg/_version.py
tsdisagg/datasets.py
tsdisagg/time_conversion.py
tsdisagg/ts_disagg.py
tsdisagg-1.3.2.dist-info/METADATA
tsdisagg-1.3.2.dist-info/WHEEL
tsdisagg-1.3.2.dist-info/licenses/LICENSE
tsdisagg-1.3.2.dist-info/RECORD
