Metadata-Version: 2.4
Name: tsdisagg
Version: 1.3.2
Summary: Temporal Disaggregation of Time Series Data in Python
Project-URL: Repository, https://github.com/jessegrabowski/tsdisagg.git
Project-URL: Issues, https://github.com/jessegrabowski/tsdisagg/issues
Author-email: Jesse Grabowski <jessegrabowski@gmail.com>
License: MIT License
License-File: LICENSE
Keywords: datetime,decomposition,econometrics,time series
Classifier: Development Status :: 4 - Beta
Classifier: Intended Audience :: Science/Research
Classifier: License :: OSI Approved :: MIT License
Classifier: Programming Language :: Python
Classifier: Programming Language :: Python :: 3.11
Classifier: Programming Language :: Python :: 3.12
Classifier: Programming Language :: Python :: 3.13
Classifier: Topic :: Scientific/Engineering
Classifier: Topic :: Scientific/Engineering :: Mathematics
Requires-Dist: numpy
Requires-Dist: pandas>=2.2.0
Requires-Dist: scipy
Provides-Extra: dev
Requires-Dist: hypothesis; extra == 'dev'
Requires-Dist: pre-commit; extra == 'dev'
Requires-Dist: pytest; extra == 'dev'
Requires-Dist: pytest-cov; extra == 'dev'
